Infinitypdf/__init__.py
Infinitypdf/pdfconvtool.py
Infinitypdf/support6.py
pdfcont-0.0.1.dist-info/LICENSE.txt
pdfcont-0.0.1.dist-info/METADATA
pdfcont-0.0.1.dist-info/WHEEL
pdfcont-0.0.1.dist-info/top_level.txt
pdfcont-0.0.1.dist-info/RECORD
