Metadata-Version: 2.1
Name: pdfcont
Version: 0.0.1
Summary: PythonTutorial
Author: Developer Ashok puri And Pawan yadav
Author-email: developergautam07@gmail.com
Keywords: python,tutorial,convert to pdf,developerpawan
Classifier: Development Status :: 1 - Planning
Classifier: Intended Audience :: Developers
Classifier: Programming Language :: Python :: 3
Classifier: Operating System :: Unix
Classifier: Operating System :: MacOS :: MacOS X
Classifier: Operating System :: Microsoft :: Windows
License-File: LICENSE.txt
